domainiac/__init__.py
domainiac/functions/__init__.py
domainiac/functions/conversions.py
domainiac/functions/interpolation.py
domainiac/functions/solar.py
domainiac/functions/temperature.py
domainiac/functions/typing.py
domainiac/functions/wind.py
domainiac/managers/__init__.py
domainiac/managers/masterdata_manager.py
domainiac/managers/metering_manager.py
domainiac/managers/nwp_manager.py
domainiac/managers/outage_manager.py
domainiac/managers/plant_manager.py
domainiac/managers/resource_manager.py
domainiac/managers/unit_manager.py
domainiac/modeling/__init__.py
domainiac/modeling/nwp.py
domainiac/modeling/plant.py
domainiac/wrappers/__init__.py
domainiac/wrappers/cache_wrapper.py
domainiac-9.3.0.dist-info/METADATA
domainiac-9.3.0.dist-info/WHEEL
domainiac-9.3.0.dist-info/RECORD
