Metadata-Version: 2.4
Name: domainiac
Version: 9.3.0
Summary: Package for working with Energinet data, but with specialized functions used for Enigma.
Author: Team Enigma
Author-email: enigma@energinet.dk
Requires-Python: >=3.10
Classifier: Programming Language :: Python :: 3
Classifier: Programming Language :: Python :: 3.10
Classifier: Programming Language :: Python :: 3.11
Classifier: Programming Language :: Python :: 3.12
Classifier: Programming Language :: Python :: 3.13
Classifier: Programming Language :: Python :: 3.14
Requires-Dist: datamazing (>=5.1.6)
Requires-Dist: pandas (>=2.2.0)
Requires-Dist: pvlib (>=0.13.1)
Requires-Dist: scikit-learn (>=1.3.0)
Requires-Dist: scipy (>=1.15.3)
Requires-Dist: typeguard (>=4.2.1)
